.cvsignore
setup.py
Products/__init__.py
Products.CompositePack.egg-info/PKG-INFO
Products.CompositePack.egg-info/SOURCES.txt
Products.CompositePack.egg-info/dependency_links.txt
Products.CompositePack.egg-info/entry_points.txt
Products.CompositePack.egg-info/namespace_packages.txt
Products.CompositePack.egg-info/not-zip-safe
Products.CompositePack.egg-info/requires.txt
Products.CompositePack.egg-info/top_level.txt
Products/CompositePack/CHANGES.txt
Products/CompositePack/COPYING.txt
Products/CompositePack/CPpermissions.py
Products/CompositePack/ClassGen.py
Products/CompositePack/ConfigurationMethods.py
Products/CompositePack/LayoutRegistry.py
Products/CompositePack/README.txt
Products/CompositePack/README_TESTS.txt
Products/CompositePack/TODO.txt
Products/CompositePack/ViewletRegistry.py
Products/CompositePack/ZopePublicLicense.txt
Products/CompositePack/__init__.py
Products/CompositePack/composite.gif
Products/CompositePack/config.py
Products/CompositePack/configure.zcml
Products/CompositePack/design.py
Products/CompositePack/exceptions.py
Products/CompositePack/interfaces.py
Products/CompositePack/makefile.in
Products/CompositePack/public.py
Products/CompositePack/refresh.txt
Products/CompositePack/tool.py
Products/CompositePack/version.txt
Products/CompositePack/Extensions/Install.py
Products/CompositePack/Extensions/__init__.py
Products/CompositePack/browser/pack.azax
Products/CompositePack/browser/test.pt
Products/CompositePack/composite/__init__.py
Products/CompositePack/composite/archetype.py
Products/CompositePack/composite/fragments.py
Products/CompositePack/composite/navigationpage.py
Products/CompositePack/composite/packcomposite.py
Products/CompositePack/composite/packview.py
Products/CompositePack/composite/portlets.py
Products/CompositePack/composite/titles.py
Products/CompositePack/demo/ATCompositeDocument.py
Products/CompositePack/demo/__init__.py
Products/CompositePack/doc/doc.txt
Products/CompositePack/exportimport/__init__.py
Products/CompositePack/exportimport/compositetool.py
Products/CompositePack/exportimport/configure.zcml
Products/CompositePack/i18n/compopack-bg.po
Products/CompositePack/i18n/compopack-de.po
Products/CompositePack/i18n/compopack-es.po
Products/CompositePack/i18n/compopack-eu.po
Products/CompositePack/i18n/compopack-fr.po
Products/CompositePack/i18n/compopack-nl.po
