Metadata-Version: 1.0
Name: Products.CompositePack
Version: 1.2a1
Summary: CompositePack product
Home-page: http://pypi.python.org/pypi/Products.CompositePack
Author: Godefroid Chappelle
Author-email: gotcha@bubblenet.be
License: ZPL 2.1 (http://www.zope.org/Resources/License/ZPL-2.1)
Keywords: web application server zope zope2 cmf plone
Platform: UNKNOWN
Classifier: Development Status :: 5 - Production/Stable
Classifier: Framework :: Plone
Classifier: Framework :: Zope2
Classifier: Intended Audience :: Developers
Classifier: License :: OSI Approved :: Zope Public License
Classifier: Programming Language :: Python
Classifier: Topic :: Software Development
